cointrader/__init__.py
cointrader/bot.py
cointrader/chart.py
cointrader/cli.py
cointrader/config.py
cointrader/exchange.py
cointrader/helpers.py
cointrader/strategy.py
cointrader/exchanges/__init__.py
cointrader/exchanges/poloniex.py
cointrader/strategies/__init__.py
cointrader/strategies/trend.py
cointrader-0.4.0.dist-info/DESCRIPTION.rst
cointrader-0.4.0.dist-info/METADATA
cointrader-0.4.0.dist-info/RECORD
cointrader-0.4.0.dist-info/WHEEL
cointrader-0.4.0.dist-info/entry_points.txt
cointrader-0.4.0.dist-info/metadata.json
cointrader-0.4.0.dist-info/top_level.txt
tests/__init__.py
tests/test_cointrader.py
tests/strategies/__init__.py
tests/strategies/test_followtrend.py
