Metadata-Version: 2.0
Name: cointrader
Version: 0.4.0
Summary: Cointrader is a trading application for crypto currencies.
Home-page: https://github.com/toirl/cointrader
Author: Torsten Irländer
Author-email: torsten.irlaender@googlemail.com
License: MIT license
Keywords: cointrader
Platform: UNKNOWN
Classifier: Development Status :: 2 - Pre-Alpha
Classifier: Intended Audience :: Developers
Classifier: License :: OSI Approved :: MIT License
Classifier: Natural Language :: English
Classifier: Programming Language :: Python :: 2
Classifier: Programming Language :: Python :: 2.7
Classifier: Programming Language :: Python :: 3
Classifier: Programming Language :: Python :: 3.5
Requires-Dist: Click (>=6.0)
Requires-Dist: requests
Requires-Dist: sqlalchemy
Requires-Dist: stockstats
Requires-Dist: termcolor
Requires-Dist: terminaltables
